blueprinter/__init__.py
blueprinter/examples/inline_snippet.py
blueprinter/inline.py
blueprinter/templates.py
blueprinter-0.1.0.dist-info/WHEEL
blueprinter-0.1.0.dist-info/METADATA
blueprinter-0.1.0.dist-info/RECORD
