Metadata-Version: 2.1
Name: blueprinter
Version: 0.1.0
Summary: 
Author: MBeebe
Author-email: pyn-sol@beebe.dev
Requires-Python: >=3.7,<4.0
Classifier: Programming Language :: Python :: 3
Classifier: Programming Language :: Python :: 3.10
Classifier: Programming Language :: Python :: 3.7
Classifier: Programming Language :: Python :: 3.8
Classifier: Programming Language :: Python :: 3.9
